nbfree/__init__.py
nbfree-0.2.3.dist-info/METADATA
nbfree-0.2.3.dist-info/WHEEL
nbfree-0.2.3.dist-info/entry_points.txt
nbfree-0.2.3.dist-info/RECORD
